aid_py/__init__.py
aid_py/constants.py
aid_py/discover.py
aid_py/parser.py
aid_discovery-1.0.0.dist-info/METADATA
aid_discovery-1.0.0.dist-info/WHEEL
aid_discovery-1.0.0.dist-info/top_level.txt
aid_discovery-1.0.0.dist-info/RECORD
