Metadata-Version: 2.4
Name: aid-discovery
Version: 1.0.0
Summary: Python library for Agent Interface Discovery (AID) - v1.0.0 release
Author-email: Agent Community <maintainers@agentcommunity.org>
License: MIT
Project-URL: Homepage, https://github.com/agent-community/agent-interface-discovery
Project-URL: Repository, https://github.com/agent-community/agent-interface-discovery
Requires-Python: >=3.8
Requires-Dist: dnspython>=2.6.0
Requires-Dist: idna>=3.6
Provides-Extra: dev
Requires-Dist: pytest>=8; extra == "dev"
